README.txt
setup.cfg
setup.py
docs/INSTALL.txt
docs/LICENSE.txt
docs/NOTES.txt
docs/OpenDocument-package-v1.2-draft6.pdf
docs/OpenDocument-v1.2-draft6.pdf
odfsvn/__init__.py
odfsvn/interfaces.py
odfsvn/package.py
odfsvn/svn.py
odfsvn/utils.py
odfsvn.egg-info/PKG-INFO
odfsvn.egg-info/SOURCES.txt
odfsvn.egg-info/dependency_links.txt
odfsvn.egg-info/entry_points.txt
odfsvn.egg-info/top_level.txt
odfsvn.egg-info/zip-safe
odfsvn/scripts/__init__.py
odfsvn/scripts/main.py
tests/__init__.py
tests/testPackage.py
tests/testSvn.py
tests/testUtils.py
tests/data/testfile.odt
tests/data/test.odt/content.xml
tests/data/test.odt/meta.xml
tests/data/test.odt/mimetype
tests/data/test.odt/settings.xml
tests/data/test.odt/styles.xml
tests/data/test.odt/META-INF/manifest.xml
tests/data/test.odt/Thumbnails/thumbnail.png
