Metadata-Version: 1.0
Name: odfsvn
Version: 1.0a1
Summary: Manage ODF files in SubVersioN
Home-page: http://www.sourceforge.net/projects/odfsvn/
Author: Wichert Akkerman - Simplon
Author-email: wichert@simplon.biz
License: GPL3
Keywords: ODF SVN
Platform: UNKNOWN
Classifier: Intended Audience :: End Users/Desktop
Classifier: License :: OSI Approved :: GNU General Public License (GPL)
Classifier: Programming Language :: Python
Classifier: Topic :: Office/Business :: Office Suites
Classifier: Topic :: Text Editors :: Word Processors
